SMControlFig2StructuralFSM.v
//==============================================================================
// SMControlFig2Structural.v
// Control Unit for Sequential Multiplier (Fig2) 
// with Variables Exposed in Declaration for FSM Extraction 
//==============================================================================

module SMControl(
    input [3:0]  reset_state,

    // External Inputs for Flow
    input wire          clk, // clock
    input wire          rst, // reset
    input wire          start, // start

    // Inputs from Datapath
    // multiplier register (4)
    input wire [3:0]    mr, // 4 bit multiplier register

    // Controller Outputs to Datapath
    output          mdld, // load multiplicand register
    output          mrld, // load multiplier register
    output          rsload, // load running sum register
    output          rsclear, // clear running sum register
    output          rsshr, // shift running sum register

    output reg [3:0]    s,
    output wire [3:0] n,
    output done
);

//----------------------------------------------------------------------
// FSM States
//----------------------------------------------------------------------
   
    // reg [3:0] s; // s = state
    // // refer to them as s[3], s[2], s[1], s[0], etc
    // wire [3:0] n; // n = next_state

//----------------------------------------------------------------------
// Output Combinational Logic
//----------------------------------------------------------------------
   
    assign rsclear = (~s[3]) & (~s[2]) & (~s[1]) & (s[0]);
    assign mdld = (~s[3]) & (~s[2]) & (~s[1]) & (s[0]);
    assign mrld = (~s[3]) & (~s[2]) & (~s[1]) & (s[0]);

    assign rsload = (~s[3]) & (s[2]) & (s[1]) & (s[0])
                  | (s[3]) & (~s[2]) & (~s[1]) & (~s[0])
                  | (s[3]) & (~s[2]) & (~s[1]) & (s[0])
                  | (s[3]) & (~s[2]) & (s[1]) & (~s[0]);
    assign rsshr = (~s[3]) & (~s[2]) & (s[1]) & (s[0])
                 | (~s[3]) & (s[2]) & (~s[1]) & (~s[0])
                 | (~s[3]) & (s[2]) & (~s[1]) & (s[0])
                 | (~s[3]) & (s[2]) & (s[1]) & (~s[0]);

//----------------------------------------------------------------------
// Next State Combinational Logic
//----------------------------------------------------------------------

    assign n[3] = (~s[3]) & (~s[2]) & (s[1]) & (s[0]) & (mr[1])
                | (~s[3]) & (s[2]) & (~s[1]) & (~s[0]) & (mr[2])
                | (~s[3]) & (s[2]) & (~s[1]) & (s[0]) & (mr[3]);

    assign n[2] = (~s[3]) & (~s[2]) & (s[1]) & (~s[0]) & (mr[0])
                | (~s[3]) & (~s[2]) & (s[1]) & (s[0]) & (~mr[1])
                | (s[3]) & (~s[2]) & (~s[1]) & (~s[0])
                | (~s[3]) & (s[2]) & (~s[1]) & (~s[0]) & (~mr[2])
                | (s[3]) & (~s[2]) & (~s[1]) & (s[0])
                | (~s[3]) & (s[2]) & (~s[1]) & (s[0]) & (~mr[3])
                | (s[3]) & (~s[2]) & (s[1]) & (~s[0]);

    assign n[1] = (~s[3]) & (~s[2]) & (~s[1]) & (s[0])
                | (~s[3]) & (~s[2]) & (s[1]) & (~s[0])
                | (~s[3]) & (s[2]) & (s[1]) & (s[0])
                | (~s[3]) & (s[2]) & (~s[1]) & (s[0])
                | (s[3]) & (~s[2]) & (s[1]) & (~s[0]);

    assign n[0] = (~s[3]) & (~s[2]) & (~s[1]) & (~s[0]) & (start)
                | (~s[3]) & (~s[2]) & (s[1]) & (~s[0])
                | (~s[3]) & (s[2]) & (s[1]) & (s[0])
                | (~s[3]) & (s[2]) & (~s[1]) & (~s[0])
                | (s[3]) & (~s[2]) & (~s[1]) & (s[0]);

//----------------------------------------------------------------------
// State Update Sequential Logic
//----------------------------------------------------------------------

     always @(posedge clk) begin
		if (rst) begin
			s <= reset_state; // 4'b0000;
		end
		else begin
			s <= n;
		end
	end

endmodule

SMTTFSMBF.t.v
//===============================================================================
// Brute Force Testbench for 4-bit Controller
// setup code adapted from ECE206 testing material and Marina's code
// algorithm and implementation of algorithm is my own
//===============================================================================
`timescale 1ns/100ps

`define ASSERT_EQ(ONE, TWO, MSG)               \
	begin                                      \
		if ((ONE) !== (TWO)) begin             \
			$display("\t[FAILURE]:%s", (MSG)); \
			errors = errors + 1;               \
		end                                    \
	end #0

`define SET(VAR, VALUE) $display("Setting %s to %s...", "VAR", "VALUE"); #1; VAR = (VALUE); #1

`define CLOCK $display("Pressing uclk..."); #1; clk = 1; #1; clk = 0; #1

`define SHOW_STATE(STATE) $display("\nEntering State: %s\n-----------------------------------", STATE)

module SMControlTest;
    parameter NUM_BITS = 4;

	// Local Vars
	reg clk = 0;
	reg rst = 0;
	reg start = 0;
	reg [NUM_BITS - 1:0] mr = 4'd0;
    wire [2 * NUM_BITS - 1:0] product;
    wire mdld;
    wire mrld;
    wire rsload;
    wire rsclear;
    wire rsshr;
    wire [NUM_BITS - 1:0] s;
    wire [NUM_BITS - 1:0] n;
    wire done;

	reg [NUM_BITS - 1:0] reset_state = 4'd0;

	// Error Counts
	reg [7:0] errors = 0;

	// VCD Dump
	initial begin
		$dumpfile("SMTTFSMFig#BF.vcd"); // change this for desired output .vcd name
		$dumpvars;
	end

    SMControl control (
        .reset_state    (reset_state),

        // External Inputs for Flow
        .clk            (clk), // clock
        .rst            (rst), // reset
        .start          (start), // start

        // Inputs from Datapath
        // multiplier register (4)
        .mr             (mr), // 4 bit multiplier register

        // Controller Outputs to Datapath
        .mdld           (mdld), // load multiplicand register
        .mrld           (mrld), // load multiplier register
        .rsload         (rsload), // load running sum register
        .rsclear        (rsclear), // clear running sum register
        .rsshr          (rsshr), // shift running sum register

        .s              (s),
        .n              (n),
        .done           (done)
    );

    integer multiplier;
    integer st;
    integer rs;

	// Main Test Logic 
    initial begin

        for (rs = 0; rs <= 4'd15; rs = rs + 1) begin
           
            // change the RESET_STATE for the control unit            
            $display("\nTest with RESET_STATE = %b", rs);
            `SET(reset_state, rs);

            // cycle through all (multiplier, start) combinations
            for (multiplier = 0; multiplier <= 4'd15; multiplier = multiplier + 1) begin
                
                $display("\nMULTIPLIER = %b", multiplier);

                for (st = 0; st <= 1; st = st + 1) begin

                    $display("\nSTART = %b", st);

                    `SET(mr, multiplier);
                    `SET(start, st);
                    `SET(rst, 1);
                    `CLOCK;

                    `SET(rst, 0);
                    `CLOCK;
                end
            end

            if (reset_state == 4'd15) begin
                $display("\nAll states have been tested.");
                $finish;
            end
        end
    end

endmodule

Fig4/SMTTInputBruteForce.vcd
$date
	Wed Apr 09 23:59:12 2025
$end
$version
	Icarus Verilog
$end
$timescale
	100ps
$end
$scope module SMControlTest $end
$var wire 4 ! s [3:0] $end
$var wire 1 " rsshr $end
$var wire 1 # rsload $end
$var wire 1 $ rsclear $end
$var wire 4 % n [3:0] $end
$var wire 1 & mrld $end
$var wire 1 ' mdld $end
$var wire 1 ( done $end
$var parameter 32 ) NUM_BITS $end
$var reg 1 * clk $end
$var reg 8 + errors [7:0] $end
$var reg 4 , mr [3:0] $end
$var reg 4 - reset_state [3:0] $end
$var reg 1 . rst $end
$var reg 1 / start $end
$var integer 32 0 multiplier [31:0] $end
$var integer 32 1 rs [31:0] $end
$var integer 32 2 st [31:0] $end
$scope module control $end
$var wire 1 * clk $end
$var wire 1 ( done $end
$var wire 1 ' mdld $end
$var wire 4 3 mr [3:0] $end
$var wire 1 & mrld $end
$var wire 4 4 reset_state [3:0] $end
$var wire 1 $ rsclear $end
$var wire 1 # rsload $end
$var wire 1 " rsshr $end
$var wire 1 . rst $end
$var wire 1 / start $end
$var wire 4 5 n [3:0] $end
$var reg 4 6 s [3:0] $end
$upscope $end
$upscope $end
$enddefinitions $end
$comment Show the parameter values. $end
$dumpall
b100 )
$end
#0
$dumpvars
bx 6
bx 5
b0 4
b0 3
bx 2
b0 1
bx 0
0/
0.
b0 -
b0 ,
b0 +
0*
x(
x'
x&
bx %
x$
x#
x"
bx !
$end
#20
b0 2
b0 0
#70
1.
#90
0#
0"
b0 %
b0 5
0(
0$
0'
0&
b0 !
b0 6
1*
#100
0*
#120
0.
#140
1*
#150
0*
#160
b1 2
#190
b1 %
b1 5
1/
#210
1.
#230
1*
#240
0*
#260
0.
#280
b10 %
b10 5
1$
1'
1&
b1 !
b1 6
1*
#290
0*
#300
b1 0
b0 2
#310
b1 ,
b1 3
#330
0/
#350
1.
#370
b0 %
b0 5
0$
0'
0&
b0 !
b0 6
1*
#380
0*
#400
0.
#420
1*
#430
0*
#440
b1 2
#470
b1 %
b1 5
1/
#490
1.
#510
1*
#520
0*
#540
0.
#560
b10 %
b10 5
1$
1'
1&
b1 !
b1 6
1*
#570
0*
#580
b10 0
b0 2
#590
b10 ,
b10 3
#610
0/
#630
1.
#650
b0 %
b0 5
0$
0'
0&
b0 !
b0 6
1*
#660
0*
#680
0.
#700
1*
#710
0*
#720
b1 2
#750
b1 %
b1 5
1/
#770
1.
#790
1*
#800
0*
#820
0.
#840
b10 %
b10 5
1$
1'
1&
b1 !
b1 6
1*
#850
0*
#860
b11 0
b0 2
#870
b11 ,
b11 3
#890
0/
#910
1.
#930
b0 %
b0 5
0$
0'
0&
b0 !
b0 6
1*
#940
0*
#960
0.
#980
1*
#990
0*
#1000
b1 2
#1030
b1 %
b1 5
1/
#1050
1.
#1070
1*
#1080
0*
#1100
0.
#1120
b10 %
b10 5
1$
1'
1&
b1 !
b1 6
1*
#1130
0*
#1140
b100 0
b0 2
#1150
b100 ,
b100 3
#1170
0/
#1190
1.
#1210
b0 %
b0 5
0$
0'
0&
b0 !
b0 6
1*
#1220
0*
#1240
0.
#1260
1*
#1270
0*
#1280
b1 2
#1310
b1 %
b1 5
1/
#1330
1.
#1350
1*
#1360
0*
#1380
0.
#1400
b10 %
b10 5
1$
1'
1&
b1 !
b1 6
1*
#1410
0*
#1420
b101 0
b0 2
#1430
b101 ,
b101 3
#1450
0/
#1470
1.
#1490
b0 %
b0 5
0$
0'
0&
b0 !
b0 6
1*
#1500
0*
#1520
0.
#1540
1*
#1550
0*
#1560
b1 2
#1590
b1 %
b1 5
1/
#1610
1.
#1630
1*
#1640
0*
#1660
0.
#1680
b10 %
b10 5
1$
1'
1&
b1 !
b1 6
1*
#1690
0*
#1700
b110 0
b0 2
#1710
b110 ,
b110 3
#1730
0/
#1750
1.
#1770
b0 %
b0 5
0$
0'
0&
b0 !
b0 6
1*
#1780
0*
#1800
0.
#1820
1*
#1830
0*
#1840
b1 2
#1870
b1 %
b1 5
1/
#1890
1.
#1910
1*
#1920
0*
#1940
0.
#1960
b10 %
b10 5
1$
1'
1&
b1 !
b1 6
1*
#1970
0*
#1980
b111 0
b0 2
#1990
b111 ,
b111 3
#2010
0/
#2030
1.
#2050
b0 %
b0 5
0$
0'
0&
b0 !
b0 6
1*
#2060
0*
#2080
0.
#2100
1*
#2110
0*
#2120
b1 2
#2150
b1 %
b1 5
1/
#2170
1.
#2190
1*
#2200
0*
#2220
0.
#2240
b10 %
b10 5
1$
1'
1&
b1 !
b1 6
1*
#2250
0*
#2260
b1000 0
b0 2
#2270
b1000 ,
b1000 3
#2290
0/
#2310
1.
#2330
b0 %
b0 5
0$
0'
0&
b0 !
b0 6
1*
#2340
0*
#2360
0.
#2380
1*
#2390
0*
#2400
b1 2
#2430
b1 %
b1 5
1/
#2450
1.
#2470
1*
#2480
0*
#2500
0.
#2520
b10 %
b10 5
1$
1'
1&
b1 !
b1 6
1*
#2530
0*
#2540
b1001 0
b0 2
#2550
b1001 ,
b1001 3
#2570
0/
#2590
1.
#2610
b0 %
b0 5
0$
0'
0&
b0 !
b0 6
1*
#2620
0*
#2640
0.
#2660
1*
#2670
0*
#2680
b1 2
#2710
b1 %
b1 5
1/
#2730
1.
#2750
1*
#2760
0*
#2780
0.
#2800
b10 %
b10 5
1$
1'
1&
b1 !
b1 6
1*
#2810
0*
#2820
b1010 0
b0 2
#2830
b1010 ,
b1010 3
#2850
0/
#2870
1.
#2890
b0 %
b0 5
0$
0'
0&
b0 !
b0 6
1*
#2900
0*
#2920
0.
#2940
1*
#2950
0*
#2960
b1 2
#2990
b1 %
b1 5
1/
#3010
1.
#3030
1*
#3040
0*
#3060
0.
#3080
b10 %
b10 5
1$
1'
1&
b1 !
b1 6
1*
#3090
0*
#3100
b1011 0
b0 2
#3110
b1011 ,
b1011 3
#3130
0/
#3150
1.
#3170
b0 %
b0 5
0$
0'
0&
b0 !
b0 6
1*
#3180
0*
#3200
0.
#3220
1*
#3230
0*
#3240
b1 2
#3270
b1 %
b1 5
1/
#3290
1.
#3310
1*
#3320
0*
#3340
0.
#3360
b10 %
b10 5
1$
1'
1&
b1 !
b1 6
1*
#3370
0*
#3380
b1100 0
b0 2
#3390
b1100 ,
b1100 3
#3410
0/
#3430
1.
#3450
b0 %
b0 5
0$
0'
0&
b0 !
b0 6
1*
#3460
0*
#3480
0.
#3500
1*
#3510
0*
#3520
b1 2
#3550
b1 %
b1 5
1/
#3570
1.
#3590
1*
#3600
0*
#3620
0.
#3640
b10 %
b10 5
1$
1'
1&
b1 !
b1 6
1*
#3650
0*
#3660
b1101 0
b0 2
#3670
b1101 ,
b1101 3
#3690
0/
#3710
1.
#3730
b0 %
b0 5
0$
0'
0&
b0 !
b0 6
1*
#3740
0*
#3760
0.
#3780
1*
#3790
0*
#3800
b1 2
#3830
b1 %
b1 5
1/
#3850
1.
#3870
1*
#3880
0*
#3900
0.
#3920
b10 %
b10 5
1$
1'
1&
b1 !
b1 6
1*
#3930
0*
#3940
b1110 0
b0 2
#3950
b1110 ,
b1110 3
#3970
0/
#3990
1.
#4010
b0 %
b0 5
0$
0'
0&
b0 !
b0 6
1*
#4020
0*
#4040
0.
#4060
1*
#4070
0*
#4080
b1 2
#4110
b1 %
b1 5
1/
#4130
1.
#4150
1*
#4160
0*
#4180
0.
#4200
b10 %
b10 5
1$
1'
1&
b1 !
b1 6
1*
#4210
0*
#4220
b1111 0
b0 2
#4230
b1111 ,
b1111 3
#4250
0/
#4270
1.
#4290
b0 %
b0 5
0$
0'
0&
b0 !
b0 6
1*
#4300
0*
#4320
0.
#4340
1*
#4350
0*
#4360
b1 2
#4390
b1 %
b1 5
1/
#4410
1.
#4430
1*
#4440
0*
#4460
0.
#4480
b10 %
b10 5
1$
1'
1&
b1 !
b1 6
1*
#4490
0*
#4500
b1 1
b10000 0
b10 2
#4510
b1 -
b1 4
#4520
b0 2
b0 0
#4530
b0 ,
b0 3
#4550
0/
#4570
1.
#4590
1*
#4600
0*
#4620
0.
#4640
b1011 %
b1011 5
0$
0'
0&
b10 !
b10 6
1*
#4650
0*
#4660
b1 2
#4690
1/
#4710
1.
#4730
b10 %
b10 5
0"
1$
1'
1&
b1 !
b1 6
1*
#4740
0*
#4760
0.
#4780
b1011 %
b1011 5
0$
0'
0&
b10 !
b10 6
1*
#4790
0*
#4800
b1 0
b0 2
#4810
b111 %
b111 5
b1 ,
b1 3
#4830
0/
#4850
1.
#4870
0"
b10 %
b10 5
1$
1'
1&
b1 !
b1 6
1*
#4880
0*
#4900
0.
#4920
b111 %
b111 5
0$
0'
0&
b10 !
b10 6
1*
#4930
0*
#4940
b1 2
#4970
1/
#4990
1.
#5010
0"
b10 %
b10 5
1$
1'
1&
b1 !
b1 6
1*
#5020
0*
#5040
0.
#5060
b111 %
b111 5
0$
0'
0&
b10 !
b10 6
1*
#5070
0*
#5080
b10 0
b0 2
#5090
b1011 %
b1011 5
b10 ,
b10 3
#5110
0/
#5130
1.
#5150
b10 %
b10 5
0"
1$
1'
1&
b1 !
b1 6
1*
#5160
0*
#5180
0.
#5200
b1011 %
b1011 5
0$
0'
0&
b10 !
b10 6
1*
#5210
0*
#5220
b1 2
#5250
1/
#5270
1.
#5290
b10 %
b10 5
0"
1$
1'
1&
b1 !
b1 6
1*
#5300
0*
#5320
0.
#5340
b1011 %
b1011 5
0$
0'
0&
b10 !
b10 6
1*
#5350
0*
#5360
b11 0
b0 2
#5370
b111 %
b111 5
b11 ,
b11 3
#5390
0/
#5410
1.
#5430
0"
b10 %
b10 5
1$
1'
1&
b1 !
b1 6
1*
#5440
0*
#5460
0.
#5480
b111 %
b111 5
0$
0'
0&
b10 !
b10 6
1*
#5490
0*
#5500
b1 2
#5530
1/
#5550
1.
#5570
0"
b10 %
b10 5
1$
1'
1&
b1 !
b1 6
1*
#5580
0*
#5600
0.
#5620
b111 %
b111 5
0$
0'
0&
b10 !
b10 6
1*
#5630
0*
#5640
b100 0
b0 2
#5650
b1011 %
b1011 5
b100 ,
b100 3
#5670
0/
#5690
1.
#5710
b10 %
b10 5
0"
1$
1'
1&
b1 !
b1 6
1*
#5720
0*
#5740
0.
#5760
b1011 %
b1011 5
0$
0'
0&
b10 !
b10 6
1*
#5770
0*
#5780
b1 2
#5810
1/
#5830
1.
#5850
b10 %
b10 5
0"
1$
1'
1&
b1 !
b1 6
1*
#5860
0*
#5880
0.
#5900
b1011 %
b1011 5
0$
0'
0&
b10 !
b10 6
1*
#5910
0*
#5920
b101 0
b0 2
#5930
b111 %
b111 5
b101 ,
b101 3
#5950
0/
#5970
1.
#5990
0"
b10 %
b10 5
1$
1'
1&
b1 !
b1 6
1*
#6000
0*
#6020
0.
#6040
b111 %
b111 5
0$
0'
0&
b10 !
b10 6
1*
#6050
0*
#6060
b1 2
#6090
1/
#6110
1.
#6130
0"
b10 %
b10 5
1$
1'
1&
b1 !
b1 6
1*
#6140
0*
#6160
0.
#6180
b111 %
b111 5
0$
0'
0&
b10 !
b10 6
1*
#6190
0*
#6200
b110 0
b0 2
#6210
b1011 %
b1011 5
b110 ,
b110 3
#6230
0/
#6250
1.
#6270
b10 %
b10 5
0"
1$
1'
1&
b1 !
b1 6
1*
#6280
0*
#6300
0.
#6320
b1011 %
b1011 5
0$
0'
0&
b10 !
b10 6
1*
#6330
0*
#6340
b1 2
#6370
1/
#6390
1.
#6410
b10 %
b10 5
0"
1$
1'
1&
b1 !
b1 6
1*
#6420
0*
#6440
0.
#6460
b1011 %
b1011 5
0$
0'
0&
b10 !
b10 6
1*
#6470
0*
#6480
b111 0
b0 2
#6490
b111 %
b111 5
b111 ,
b111 3
#6510
0/
#6530
1.
#6550
0"
b10 %
b10 5
1$
1'
1&
b1 !
b1 6
1*
#6560
0*
#6580
0.
#6600
b111 %
b111 5
0$
0'
0&
b10 !
b10 6
1*
#6610
0*
#6620
b1 2
#6650
1/
#6670
1.
#6690
0"
b10 %
b10 5
1$
1'
1&
b1 !
b1 6
1*
#6700
0*
#6720
0.
#6740
b111 %
b111 5
0$
0'
0&
b10 !
b10 6
1*
#6750
0*
#6760
b1000 0
b0 2
#6770
b1011 %
b1011 5
b1000 ,
b1000 3
#6790
0/
#6810
1.
#6830
b10 %
b10 5
0"
1$
1'
1&
b1 !
b1 6
1*
#6840
0*
#6860
0.
#6880
b1011 %
b1011 5
0$
0'
0&
b10 !
b10 6
1*
#6890
0*
#6900
b1 2
#6930
1/
#6950
1.
#6970
b10 %
b10 5
0"
1$
1'
1&
b1 !
b1 6
1*
#6980
0*
#7000
0.
#7020
b1011 %
b1011 5
0$
0'
0&
b10 !
b10 6
1*
#7030
0*
#7040
b1001 0
b0 2
#7050
b111 %
b111 5
b1001 ,
b1001 3
#7070
0/
#7090
1.
#7110
0"
b10 %
b10 5
1$
1'
1&
b1 !
b1 6
1*
#7120
0*
#7140
0.
#7160
b111 %
b111 5
0$
0'
0&
b10 !
b10 6
1*
#7170
0*
#7180
b1 2
#7210
1/
#7230
1.
#7250
0"
b10 %
b10 5
1$
1'
1&
b1 !
b1 6
1*
#7260
0*
#7280
0.
#7300
b111 %
b111 5
0$
0'
0&
b10 !
b10 6
1*
#7310
0*
#7320
b1010 0
b0 2
#7330
b1011 %
b1011 5
b1010 ,
b1010 3
#7350
0/
#7370
1.
#7390
b10 %
b10 5
0"
1$
1'
1&
b1 !
b1 6
1*
#7400
0*
#7420
0.
#7440
b1011 %
b1011 5
0$
0'
0&
b10 !
b10 6
1*
#7450
0*
#7460
b1 2
#7490
1/
#7510
1.
#7530
b10 %
b10 5
0"
1$
1'
1&
b1 !
b1 6
1*
#7540
0*
#7560
0.
#7580
b1011 %
b1011 5
0$
0'
0&
b10 !
b10 6
1*
#7590
0*
#7600
b1011 0
b0 2
#7610
b111 %
b111 5
b1011 ,
b1011 3
#7630
0/
#7650
1.
#7670
0"
b10 %
b10 5
1$
1'
1&
b1 !
b1 6
1*
#7680
0*
#7700
0.
#7720
b111 %
b111 5
0$
0'
0&
b10 !
b10 6
1*
#7730
0*
#7740
b1 2
#7770
1/
#7790
1.
#7810
0"
b10 %
b10 5
1$
1'
1&
b1 !
b1 6
1*
#7820
0*
#7840
0.
#7860
b111 %
b111 5
0$
0'
0&
b10 !
b10 6
1*
#7870
0*
#7880
b1100 0
b0 2
#7890
b1011 %
b1011 5
b1100 ,
b1100 3
#7910
0/
#7930
1.
#7950
b10 %
b10 5
0"
1$
1'
1&
b1 !
b1 6
1*
#7960
0*
#7980
0.
#8000
b1011 %
b1011 5
0$
0'
0&
b10 !
b10 6
1*
#8010
0*
#8020
b1 2
#8050
1/
#8070
1.
#8090
b10 %
b10 5
0"
1$
1'
1&
b1 !
b1 6
1*
#8100
0*
#8120
0.
#8140
b1011 %
b1011 5
0$
0'
0&
b10 !
b10 6
1*
#8150
0*
#8160
b1101 0
b0 2
#8170
b111 %
b111 5
b1101 ,
b1101 3
#8190
0/
#8210
1.
#8230
0"
b10 %
b10 5
1$
1'
1&
b1 !
b1 6
1*
#8240
0*
#8260
0.
#8280
b111 %
b111 5
0$
0'
0&
b10 !
b10 6
1*
#8290
0*
#8300
b1 2
#8330
1/
#8350
1.
#8370
0"
b10 %
b10 5
1$
1'
1&
b1 !
b1 6
1*
#8380
0*
#8400
0.
#8420
b111 %
b111 5
0$
0'
0&
b10 !
b10 6
1*
#8430
0*
#8440
b1110 0
b0 2
#8450
b1011 %
b1011 5
b1110 ,
b1110 3
#8470
0/
#8490
1.
#8510
b10 %
b10 5
0"
1$
1'
1&
b1 !
b1 6
1*
#8520
0*
#8540
0.
#8560
b1011 %
b1011 5
0$
0'
0&
b10 !
b10 6
1*
#8570
0*
#8580
b1 2
#8610
1/
#8630
1.
#8650
b10 %
b10 5
0"
1$
1'
1&
b1 !
b1 6
1*
#8660
0*
#8680
0.
#8700
b1011 %
b1011 5
0$
0'
0&
b10 !
b10 6
1*
#8710
0*
#8720
b1111 0
b0 2
#8730
b111 %
b111 5
b1111 ,
b1111 3
#8750
0/
#8770
1.
#8790
0"
b10 %
b10 5
1$
1'
1&
b1 !
b1 6
1*
#8800
0*
#8820
0.
#8840
b111 %
b111 5
0$
0'
0&
b10 !
b10 6
1*
#8850
0*
#8860
b1 2
#8890
1/
#8910
1.
#8930
0"
b10 %
b10 5
1$
1'
1&
b1 !
b1 6
1*
#8940
0*
#8960
0.
#8980
b111 %
b111 5
0$
0'
0&
b10 !
b10 6
1*
#8990
0*
#9000
b10 1
b10000 0
b10 2
#9010
b10 -
b10 4
#9020
b0 2
b0 0
#9030
b1011 %
b1011 5
b0 ,
b0 3
#9050
0/
#9070
1.
#9090
1*
#9100
0*
#9120
0.
#9140
b11 %
b11 5
0"
b1011 !
b1011 6
1*
#9150
0*
#9160
b1 2
#9190
1/
#9210
1.
#9230
0#
b1011 %
b1011 5
b10 !
b10 6
1*
#9240
0*
#9260
0.
#9280
b11 %
b11 5
0"
b1011 !
b1011 6
1*
#9290
0*
#9300
b1 0
b0 2
#9310
b1 ,
b1 3
#9330
0/
#9350
1.
#9370
0#
b111 %
b111 5
b10 !
b10 6
1*
#9380
0*
#9400
0.
#9420
1#
0"
b11 %
b11 5
b111 !
b111 6
1*
#9430
0*
#9440
b1 2
#9470
1/
#9490
1.
#9510
b111 %
b111 5
0#
0"
0(
b10 !
b10 6
1*
#9520
0*
#9540
0.
#9560
1#
0"
b11 %
b11 5
b111 !
b111 6
1*
#9570
0*
#9580
b10 0
b0 2
#9590
b10 ,
b10 3
#9610
0/
#9630
1.
#9650
b1011 %
b1011 5
0#
0"
0(
b10 !
b10 6
1*
#9660
0*
#9680
0.
#9700
b11 %
b11 5
0"
b1011 !
b1011 6
1*
#9710
0*
#9720
b1 2
#9750
1/
#9770
1.
#9790
0#
b1011 %
b1011 5
b10 !
b10 6
1*
#9800
0*
#9820
0.
#9840
b11 %
b11 5
0"
b1011 !
b1011 6
1*
#9850
0*
#9860
b11 0
b0 2
#9870
b11 ,
b11 3
#9890
0/
#9910
1.
#9930
0#
b111 %
b111 5
b10 !
b10 6
1*
#9940
0*
#9960
0.
#9980
1#
0"
b11 %
b11 5
b111 !
b111 6
1*
#9990
0*
#10000
b1 2
#10030
1/
#10050
1.
#10070
b111 %
b111 5
0#
0"
0(
b10 !
b10 6
1*
#10080
0*
#10100
0.
#10120
1#
0"
b11 %
b11 5
b111 !
b111 6
1*
#10130
0*
#10140
b100 0
b0 2
#10150
b100 ,
b100 3
#10170
0/
#10190
1.
#10210
b1011 %
b1011 5
0#
0"
0(
b10 !
b10 6
1*
#10220
0*
#10240
0.
#10260
b11 %
b11 5
0"
b1011 !
b1011 6
1*
#10270
0*
#10280
b1 2
#10310
1/
#10330
1.
#10350
0#
b1011 %
b1011 5
b10 !
b10 6
1*
#10360
0*
#10380
0.
#10400
b11 %
b11 5
0"
b1011 !
b1011 6
1*
#10410
0*
#10420
b101 0
b0 2
#10430
b101 ,
b101 3
#10450
0/
#10470
1.
#10490
0#
b111 %
b111 5
b10 !
b10 6
1*
#10500
0*
#10520
0.
#10540
1#
0"
b11 %
b11 5
b111 !
b111 6
1*
#10550
0*
#10560
b1 2
#10590
1/
#10610
1.
#10630
b111 %
b111 5
0#
0"
0(
b10 !
b10 6
1*
#10640
0*
#10660
0.
#10680
1#
0"
b11 %
b11 5
b111 !
b111 6
1*
#10690
0*
#10700
b110 0
b0 2
#10710
b110 ,
b110 3
#10730
0/
#10750
1.
#10770
b1011 %
b1011 5
0#
0"
0(
b10 !
b10 6
1*
#10780
0*
#10800
0.
#10820
b11 %
b11 5
0"
b1011 !
b1011 6
1*
#10830
0*
#10840
b1 2
#10870
1/
#10890
1.
#10910
0#
b1011 %
b1011 5
b10 !
b10 6
1*
#10920
0*
#10940
0.
#10960
b11 %
b11 5
0"
b1011 !
b1011 6
1*
#10970
0*
#10980
b111 0
b0 2
#10990
b111 ,
b111 3
#11010
0/
#11030
1.
#11050
0#
b111 %
b111 5
b10 !
b10 6
1*
#11060
0*
#11080
0.
#11100
1#
0"
b11 %
b11 5
b111 !
b111 6
1*
#11110
0*
#11120
b1 2
#11150
1/
#11170
1.
#11190
b111 %
b111 5
0#
0"
0(
b10 !
b10 6
1*
#11200
0*
#11220
0.
#11240
1#
0"
b11 %
b11 5
b111 !
b111 6
1*
#11250
0*
#11260
b1000 0
b0 2
#11270
b1000 ,
b1000 3
#11290
0/
#11310
1.
#11330
b1011 %
b1011 5
0#
0"
0(
b10 !
b10 6
1*
#11340
0*
#11360
0.
#11380
b11 %
b11 5
0"
b1011 !
b1011 6
1*
#11390
0*
#11400
b1 2
#11430
1/
#11450
1.
#11470
0#
b1011 %
b1011 5
b10 !
b10 6
1*
#11480
0*
#11500
0.
#11520
b11 %
b11 5
0"
b1011 !
b1011 6
1*
#11530
0*
#11540
b1001 0
b0 2
#11550
b1001 ,
b1001 3
#11570
0/
#11590
1.
#11610
0#
b111 %
b111 5
b10 !
b10 6
1*
#11620
0*
#11640
0.
#11660
1#
0"
b11 %
b11 5
b111 !
b111 6
1*
#11670
0*
#11680
b1 2
#11710
1/
#11730
1.
#11750
b111 %
b111 5
0#
0"
0(
b10 !
b10 6
1*
#11760
0*
#11780
0.
#11800
1#
0"
b11 %
b11 5
b111 !
b111 6
1*
#11810
0*
#11820
b1010 0
b0 2
#11830
b1010 ,
b1010 3
#11850
0/
#11870
1.
#11890
b1011 %
b1011 5
0#
0"
0(
b10 !
b10 6
1*
#11900
0*
#11920
0.
#11940
b11 %
b11 5
0"
b1011 !
b1011 6
1*
#11950
0*
#11960
b1 2
#11990
1/
#12010
1.
#12030
0#
b1011 %
b1011 5
b10 !
b10 6
1*
#12040
0*
#12060
0.
#12080
b11 %
b11 5
0"
b1011 !
b1011 6
1*
#12090
0*
#12100
b1011 0
b0 2
#12110
b1011 ,
b1011 3
#12130
0/
#12150
1.
#12170
0#
b111 %
b111 5
b10 !
b10 6
1*
#12180
0*
#12200
0.
#12220
1#
0"
b11 %
b11 5
b111 !
b111 6
1*
#12230
0*
#12240
b1 2
#12270
1/
#12290
1.
#12310
b111 %
b111 5
0#
0"
0(
b10 !
b10 6
1*
#12320
0*
#12340
0.
#12360
1#
0"
b11 %
b11 5
b111 !
b111 6
1*
#12370
0*
#12380
b1100 0
b0 2
#12390
b1100 ,
b1100 3
#12410
0/
#12430
1.
#12450
b1011 %
b1011 5
0#
0"
0(
b10 !
b10 6
1*
#12460
0*
#12480
0.
#12500
b11 %
b11 5
0"
b1011 !
b1011 6
1*
#12510
0*
#12520
b1 2
#12550
1/
#12570
1.
#12590
0#
b1011 %
b1011 5
b10 !
b10 6
1*
#12600
0*
#12620
0.
#12640
b11 %
b11 5
0"
b1011 !
b1011 6
1*
#12650
0*
#12660
b1101 0
b0 2
#12670
b1101 ,
b1101 3
#12690
0/
#12710
1.
#12730
0#
b111 %
b111 5
b10 !
b10 6
1*
#12740
0*
#12760
0.
#12780
1#
0"
b11 %
b11 5
b111 !
b111 6
1*
#12790
0*
#12800
b1 2
#12830
1/
#12850
1.
#12870
b111 %
b111 5
0#
0"
0(
b10 !
b10 6
1*
#12880
0*
#12900
0.
#12920
1#
0"
b11 %
b11 5
b111 !
b111 6
1*
#12930
0*
#12940
b1110 0
b0 2
#12950
b1110 ,
b1110 3
#12970
0/
#12990
1.
#13010
b1011 %
b1011 5
0#
0"
0(
b10 !
b10 6
1*
#13020
0*
#13040
0.
#13060
b11 %
b11 5
0"
b1011 !
b1011 6
1*
#13070
0*
#13080
b1 2
#13110
1/
#13130
1.
#13150
0#
b1011 %
b1011 5
b10 !
b10 6
1*
#13160
0*
#13180
0.
#13200
b11 %
b11 5
0"
b1011 !
b1011 6
1*
#13210
0*
